typeconstraints
