Metadata-Version: 1.1
Name: typeconstraints
Version: 0.9.4
Summary: Type Constraints Decorator
Home-page: https://steemit.com/@mattockfs
Author: Rob J Meijer
Author-email: pibara@gmail.com
License: BSD
Download-URL: https://github.com/pibara-utopian/typeconstraints
Keywords: assert type constraints
Platform: UNKNOWN
Classifier: Development Status :: 4 - Beta
Classifier: Intended Audience :: Developers
Classifier: Topic :: Software Development :: Libraries
Classifier: License :: OSI Approved :: BSD License
Classifier: Programming Language :: Python :: 3
Classifier: Operating System :: OS Independent
Classifier: Environment :: Other Environment
